<?xml version="1.0"?>
<VersionInfoTable>
	<ItemName>fn_YBLGovtSBCEligibilityComputation</ItemName>
	<IsEntryDeleted>false</IsEntryDeleted>
	<VersionElement VersionId="7">
		<User>admin</User>
		<Comment> theBlazeMessageBT.foir =foir; line added</Comment>
		<Timestamp>14 Jun 2023 06:04:13 GMT</Timestamp>
	</VersionElement>
	<VersionElement VersionId="6">
		<User>admin</User>
		<Comment></Comment>
		<Timestamp>16 Dec 2021 12:36:44 GMT</Timestamp>
	</VersionElement>
	<VersionElement VersionId="5">
		<User>admin</User>
		<Comment>insurance amount is removed</Comment>
		<Timestamp>16 Dec 2021 07:48:43 GMT</Timestamp>
	</VersionElement>
	<VersionElement VersionId="4">
		<User>admin</User>
		<Comment>assetCategory and riskCategory append set the assetType</Comment>
		<Timestamp>4 Feb 2021 12:46:00 GMT</Timestamp>
	</VersionElement>
	<VersionElement VersionId="3">
		<User>admin</User>
		<Comment>YBL empCode updated to 84299</Comment>
		<Timestamp>7 Nov 2020 11:17:42 GMT</Timestamp>
	</VersionElement>
	<VersionElement VersionId="2">
		<User>admin</User>
		<Comment>IIR Norms Change</Comment>
		<Timestamp>29 Oct 2020 10:02:02 GMT</Timestamp>
	</VersionElement>
	<VersionElement VersionId="1">
		<User>admin</User>
		<Comment>Initial Version</Comment>
		<Timestamp>13 Jul 2020 08:59:27 GMT</Timestamp>
	</VersionElement>
</VersionInfoTable>
